liburlparser/__init__.py
liburlparser/__main__.py
liburlparser/_about.pyd
liburlparser/_core.pyd
liburlparser/core.py
liburlparser/public_suffix_list.dat
liburlparser/utils.py
liburlparser-1.6.1.dist-info/METADATA
liburlparser-1.6.1.dist-info/WHEEL
liburlparser-1.6.1.dist-info/entry_points.txt
liburlparser-1.6.1.dist-info/licenses/LICENSE
liburlparser-1.6.1.dist-info/RECORD
