Metadata-Version: 2.1
Name: liburlparser
Version: 1.6.1
Summary: Fastest Url parser in the world
Author-Email: Mohammad Raziei <mohammadraziei1375@gmail.com>
Classifier: Development Status :: 4 - Beta
Classifier: License :: OSI Approved :: MIT License
Classifier: Operating System :: OS Independent
Classifier: Programming Language :: C++
Classifier: Programming Language :: Python :: Implementation :: CPython
Classifier: Programming Language :: Python :: 3 :: Only
Classifier: Programming Language :: Python :: 3.8
Classifier: Programming Language :: Python :: 3.9
Classifier: Programming Language :: Python :: 3.10
Classifier: Programming Language :: Python :: 3.11
Classifier: Programming Language :: Python :: 3.12
Project-URL: Homepage, https://github.com/mohammadraziei/liburlparser
Project-URL: Bug Tracker, https://github.com/mohammadraziei/liburlparser/issues
Project-URL: Document, https://mohammadraziei.github.io/liburlparser/latest
Requires-Python: >=3.8
Requires-Dist: filelock
Provides-Extra: test
Requires-Dist: pytest-xdist; extra == "test"
Requires-Dist: requests; extra == "test"
Provides-Extra: online
Requires-Dist: requests; extra == "online"
License-File: LICENSE
